Metadata-Version: 1.0
Name: rest-django-jwt
Version: 0.0.1
Summary: eds sdk
Home-page: http://xiaoh.me
Author: xiaoh
Author-email: huoxingming@gmail.com
License: MIT Licence
Keywords: pip,datacanvas,eds,xiaoh
Platform: any
